blackhc/notebook/__init__.py
blackhc.notebook-2.0.2.dist-info/LICENSE
blackhc.notebook-2.0.2.dist-info/METADATA
blackhc.notebook-2.0.2.dist-info/WHEEL
blackhc.notebook-2.0.2.dist-info/top_level.txt
blackhc.notebook-2.0.2.dist-info/RECORD
